[
  {
    "title": "UFA365 สล็อต เว็บไซต์ใหม่ล่าสุด【EDMBET …",
    "link": "http://www.buachedhsp.moph.go.th/ios/ufa365%20%E0%B8%AA%E0%B8%A5%E0%B9%87%E0%B8%AD%E0%B8%95/",
    "snippet": "ufa365 สล็อต ค้นหาเว็บไซต์ใหม่ล่าสุดที่นำเสนอบริการสล็อตเว็บตรงและคาสิโอออนไลน์ พร้อมด้วยการแทงบอลออนไลน์ คุณจะได้รับ ...",
    "status": "found",
    "url": "http://www.buachedhsp.moph.go.th/ios/ufa365%20%E0%B8%AA%E0%B8%A5%E0%B9%87%E0%B8%AD%E0%B8%95/",
    "matches": {
      "สล็อต": [
        "...found in search result snippet: ufa365 สล็อต ค้นหาเว็บไซต์ใหม่ล่าสุดที่นำเสนอบริการสล็อตเว็บตรงและคาสิโอออนไลน์ พร้อมด้วยการแทงบอลออนไลน์ คุณจะได้รับ ......"
      ]
    },
    "total_matches": 1
  },
  {
    "title": "เกี่ยวกับเรา",
    "link": "http://www.buachedhsp.moph.go.th/bc/index.php/keiyw-kab-rea",
    "snippet": "pg joker 15 รับ 100 pg joker 15 รับ 100 ทดลองเล่นสล็อต pg ซื้อฟรีสปินได้ ไม่เด้ง pg test ทดลองเล่นสล็อต pg ซื้อฟรีสปินได้ ไม่เด้ง pg joker 15 รับ 100 777 riches pg pg สีม่วง ...",
    "status": "found",
    "url": "http://www.buachedhsp.moph.go.th/bc/index.php/keiyw-kab-rea",
    "matches": {
      "สล็อต": [
        "...found in search result snippet: pg joker 15 รับ 100 pg joker 15 รับ 100 ทดลองเล่นสล็อต pg ซื้อฟรีสปินได้ ไม่เด้ง pg test ทดลองเล่นสล็อต pg ซื้อฟรีสปินได้ ไม่เด้ง pg joker 15 รับ 100 777 riches pg pg สีม่วง ......"
      ]
    },
    "total_matches": 1
  },
  {
    "title": "รายชื่อผู้มีสิทธิ์สอบเป็นลูกจ้างชั่วคราวตำแหน่ง …",
    "link": "http://www.buachedhsp.moph.go.th/bc/index.php/khawsar-prachasamphanth/khawsar-pra-samphanth/ray-chux-phu-mi-siththi-sxb-pen-lukcang-chawkhraw-tahaenng-cea-phnakngan-phasdu-laea-phnakngan-pel",
    "snippet": "ฮานอย lotto เดลินิวส์ หวย slot true wallet สาวถ้ำสล็อต เดลินิวส์ ...",
    "status": "found",
    "url": "http://www.buachedhsp.moph.go.th/bc/index.php/khawsar-prachasamphanth/khawsar-pra-samphanth/ray-chux-phu-mi-siththi-sxb-pen-lukcang-chawkhraw-tahaenng-cea-phnakngan-phasdu-laea-phnakngan-pel",
    "matches": {
      "สล็อต": [
        "...found in search result snippet: ฮานอย lotto เดลินิวส์ หวย slot true wallet สาวถ้ำสล็อต เดลินิวส์ ......"
      ]
    },
    "total_matches": 1
  }
]