[
  {
    "title": "หมวด 4. ด านบริหารเป นเลิศด วยธรรมาภิบาล ( แผนที่ 12.",
    "link": "https://cnto.moph.go.th/mis/storage/template/1622625059.pdf",
    "snippet": "100% วัตถุประสงค เพื่อให ประชาชนได ประโยชน จากการรับบริการในโรงพยาบาลภาครัฐ สังกัดกระทรวง",
    "status": "found",
    "url": "https://cnto.moph.go.th/mis/storage/template/1622625059.pdf",
    "matches": {
      "100%": [
        "...found in HTML content but not in extracted text..."
      ]
    },
    "total_matches": 1
  },
  {
    "title": "ตัวชี้วัดที่ 9 ร อยละของตำบลที่มีระ",
    "link": "https://cnto.moph.go.th/mis/storage/template/1589430574.pdf",
    "snippet": "100 B ระยะเวลาประเมินผล -บันทึกข อมูลคัดกรองดำเนินชีวิตประจำวัน (ADL) /การประเมินสภาวะของผู สูงอายุ",
    "status": "found",
    "url": "https://cnto.moph.go.th/mis/storage/template/1589430574.pdf",
    "matches": {
      "100%": [
        "...found in HTML content but not in extracted text..."
      ]
    },
    "total_matches": 1
  },
  {
    "title": "หมวด 4. ด านบริหารเป นเลิศด วยธรรมาภิบาล ( Governance …",
    "link": "https://cnto.moph.go.th/mis/storage/template/1622624601.pdf",
    "snippet": "สูตรคำนวณตัวชี้วัด คุณภาพข อมูล = (A/B) x 100 ระยะเวลาประเมินผล 3, 6, 9 และ 12 เดือน เกณฑ การประเมิน :",
    "status": "found",
    "url": "https://cnto.moph.go.th/mis/storage/template/1622624601.pdf",
    "matches": {
      "100%": [
        "...found in HTML content but not in extracted text..."
      ]
    },
    "total_matches": 1
  },
  {
    "title": "หมวด 4. ด้านบริหารเป็นเลิศด้วยธรรมาภิบาล ( Governance …",
    "link": "https://cnto.moph.go.th/mis/storage/template/1643012566.pdf",
    "snippet": "x 100 จำนวนข้อมูล ที่มีการรับ–ส่ง ระหว่าง หน่วยบริการ และ HDC มีจำนวนข้อมูล ตรงกัน (ไม่มีการสูญหาย) ส่วนกลาง ประมวลผล เรื่องความ",
    "status": "found",
    "url": "https://cnto.moph.go.th/mis/storage/template/1643012566.pdf",
    "matches": {
      "100%": [
        "...found in HTML content but not in extracted text..."
      ]
    },
    "total_matches": 1
  },
  {
    "title": "ตัวชี้วัดที่ ร อยละของโรงพยาบาลที่ใช ยาอย างสมเหตุผล",
    "link": "https://cnto.moph.go.th/mis/storage/template/1589430823.pdf",
    "snippet": "วิธีการจัดเก็บข อมูล (A/B) x 100 แหล งข อมูล RDU = ข อมูลจาก รพ ทุกแห งในจังหวัดชัยนาท",
    "status": "found",
    "url": "https://cnto.moph.go.th/mis/storage/template/1589430823.pdf",
    "matches": {
      "100%": [
        "...found in HTML content but not in extracted text..."
      ]
    },
    "total_matches": 1
  }
]