[
  {
    "title": "Nejazzwinefest | สล็อตเว็บตรง เว็บสล็อต วอเลท API 100% ไม่มีขั้นต่ำ",
    "link": "https://www.nejazzwinefest.org/",
    "snippet": "Nejazzwinefest เว็บตรงสล็อตลิขสิทธิ์แท้ ไม่ผ่านเอเย่นต์ สล็อตเว็บตรง รวมค่ายสล็อตชั้นนำมากที่สุด สล็อต แตกหนักทุกเกม รับวอเลท เว็บ ...",
    "status": "found",
    "url": "https://www.nejazzwinefest.org/",
    "matches": {
      "สล็อต": [
        "Nejazzwinefest | สล็อตเว็บตรง เว็บสล็อต วอเลท API 10",
        "nejazzwinefest สลอตเวบตรง เวบสลอต วอเลท api 100 ไ",
        "nejazzwinefest สลอตเวบตรง เวบสลอต วอเลท api 100 ไมมขนตำ skip to",
        "itter envelope nejazzwinefest สลอตเวบตรง เวบสลอต วอเลท api 100 ไ",
        " nejazzwinefest สลอตเวบตรง เวบสลอต วอเลท api 100 ไมมขนตำ nejazzw",
        " ไมมขนตำ nejazzwinefest เวบตรงสลอตลขสทธแท ไมผานเอเยนต สลอตเวบตรง",
        "เวบตรงสลอตลขสทธแท ไมผานเอเยนต สลอตเวบตรง รวมคายสลอตชนนำมากทสด สล",
        " ไมผานเอเยนต สลอตเวบตรง รวมคายสลอตชนนำมากทสด สลอต แตกหนกทกเกม รบ",
        "อตเวบตรง รวมคายสลอตชนนำมากทสด สลอต แตกหนกทกเกม รบวอเลท เวบสลอต10",
        "ด สลอต แตกหนกทกเกม รบวอเลท เวบสลอต100 the berkshire bank northea"
      ]
    },
    "total_matches": 10
  }
]